guildpack/__init__.py
guildpack/log/__init__.py
guildpack/logs/__init__.py
guildpack/middleware/__init__.py
guildpack/middlewares/__init__.py
guildpack/response/__init__.py
guildpack/responses/__init__.py
guildpack/utils/__init__.py
guildpack-0.1.14.dist-info/LICENSE
guildpack-0.1.14.dist-info/METADATA
guildpack-0.1.14.dist-info/WHEEL
guildpack-0.1.14.dist-info/RECORD
