Metadata-Version: 2.1
Name: guildpack
Version: 0.1.14
Summary: Alias for oguild — OGuild utilities for Python projects
Home-page: https://github.com/OpsGuild/guildpack
License: MIT
Keywords: utilities,oguild,guildpack,helpers,python,opsguild,logging
Author: Hordunlarmy
Author-email: Hordunlarmy@gmail.com
Requires-Python: >=3.9
Classifier: Development Status :: 5 - Production/Stable
Classifier: Intended Audience :: Developers
Classifier: License :: OSI Approved :: MIT License
Classifier: Programming Language :: Python
Classifier: Programming Language :: Python :: 3
Classifier: Programming Language :: Python :: 3.9
Classifier: Programming Language :: Python :: 3.10
Classifier: Programming Language :: Python :: 3.11
Classifier: Programming Language :: Python :: 3.12
Classifier: Programming Language :: Python :: 3.13
Classifier: Programming Language :: Python :: 3.8
Provides-Extra: logstash
Requires-Dist: oguild (>=0.1.0)
Project-URL: Documentation, https://github.com/OpsGuild/guildpack#readme
Project-URL: Repository, https://github.com/OpsGuild/guildpack
